easy_workflow_manager/__init__.py
easy_workflow_manager/settings.ini
easy_workflow_manager/scripts/__init__.py
easy_workflow_manager/scripts/branch_from.py
easy_workflow_manager/scripts/clear_qa.py
easy_workflow_manager/scripts/deploy_to_qa.py
easy_workflow_manager/scripts/new_branch_from_source.py
easy_workflow_manager/scripts/qa_to_source.py
easy_workflow_manager/scripts/show_branches.py
easy_workflow_manager/scripts/show_qa.py
easy_workflow_manager/scripts/show_repo_info.py
easy_workflow_manager/scripts/tag_release.py
easy_workflow_manager/scripts/update_branch.py
tests/__init__.py
tests/conftest.py
tests/test_stuff.py
easy_workflow_manager-0.0.14.dist-info/LICENSE.txt
easy_workflow_manager-0.0.14.dist-info/METADATA
easy_workflow_manager-0.0.14.dist-info/WHEEL
easy_workflow_manager-0.0.14.dist-info/entry_points.txt
easy_workflow_manager-0.0.14.dist-info/top_level.txt
easy_workflow_manager-0.0.14.dist-info/RECORD
