Metadata-Version: 2.1
Name: easy-workflow-manager
Version: 0.0.14
Summary: Tools to support a straightforward branch/qa/merge/release process
Home-page: https://github.com/kenjyco/easy-workflow-manager
Download-URL: https://github.com/kenjyco/easy-workflow-manager/tarball/v0.0.14
Author: Ken
Author-email: kenjyco@gmail.com
License: MIT
Keywords: git,workflow,cli,command-line,branch,merge,qa,deploy,helper,kenjyco
Platform: UNKNOWN
Classifier: Development Status :: 3 - Alpha
Classifier: Environment :: Console
Classifier: Intended Audience :: Developers
Classifier: License :: OSI Approved :: MIT License
Classifier: Operating System :: MacOS :: MacOS X
Classifier: Operating System :: POSIX :: Linux
Classifier: Programming Language :: Python :: 3.5
Classifier: Programming Language :: Python
Classifier: Topic :: Software Development :: Libraries
Classifier: Topic :: Software Development :: Version Control :: Git
Classifier: Topic :: Utilities
License-File: LICENSE.txt
Requires-Dist: bg-helper
Requires-Dist: click (>=6.0)
Requires-Dist: dt-helper
Requires-Dist: input-helper
Requires-Dist: settings-helper
